pyhwp2md/__init__.py
pyhwp2md/cli.py
pyhwp2md/converter.py
pyhwp2md/detector.py
pyhwp2md/exceptions.py
pyhwp2md/hwp_converter.py
pyhwp2md/hwpx_converter.py
pyhwp2md/markdown/__init__.py
pyhwp2md/markdown/elements.py
pyhwp2md/markdown/table.py
pyhwp2md-0.1.3.dist-info/METADATA
pyhwp2md-0.1.3.dist-info/WHEEL
pyhwp2md-0.1.3.dist-info/entry_points.txt
pyhwp2md-0.1.3.dist-info/licenses/LICENSE
pyhwp2md-0.1.3.dist-info/RECORD
