Metadata-Version: 2.4
Name: pyhwp2md
Version: 0.1.3
Summary: Convert HWP and HWPX files to Markdown
Project-URL: Homepage, https://github.com/pitzcarraldo/pyhwp2md
Project-URL: Documentation, https://github.com/pitzcarraldo/pyhwp2md#readme
Project-URL: Repository, https://github.com/pitzcarraldo/pyhwp2md
Project-URL: Issues, https://github.com/pitzcarraldo/pyhwp2md/issues
Author: pitzcarraldo
Maintainer: pitzcarraldo
License: MIT
License-File: LICENSE
Keywords: converter,hancom,hwp,hwpx,markdown
Classifier: Development Status :: 3 - Alpha
Classifier: Intended Audience :: Developers
Classifier: License :: OSI Approved :: MIT License
Classifier: Operating System :: OS Independent
Classifier: Programming Language :: Python :: 3
Classifier: Programming Language :: Python :: 3.10
Classifier: Programming Language :: Python :: 3.11
Classifier: Programming Language :: Python :: 3.12
Classifier: Programming Language :: Python :: 3.13
Classifier: Topic :: File Formats
Classifier: Topic :: Text Processing :: Markup
Requires-Python: >=3.10
Requires-Dist: pyhwp>=0.1b12
Requires-Dist: python-hwpx>=1.9
Requires-Dist: six
Provides-Extra: dev
Requires-Dist: mypy>=1.7; extra == 'dev'
Requires-Dist: pytest-cov>=4.1; extra == 'dev'
Requires-Dist: pytest>=7.4; extra == 'dev'
Requires-Dist: ruff>=0.1; extra == 'dev'
